{
  "conveyors": [
    [
      0,
      3,
      1,
      3
    ],
    [
      1,
      3,
      2,
      3
    ],
    [
      2,
      3,
      3,
      3
    ],
    [
      3,
      3,
      4,
      3
    ],
    [
      4,
      3,
      5,
      3
    ],
    [
      5,
      3,
      6,
      3
    ],
    [
      6,
      3,
      7,
      3
    ]
  ],
  "goals": [
    {
      "amount": 40,
      "color": 2,
      "type": "collect_color"
    },
    {
      "amount": 6,
      "type": "clear_jelly"
    }
  ],
  "id": 102,
  "jelly": [
    [
      1,
      1,
      1
    ],
    [
      6,
      1,
      1
    ],
    [
      1,
      6,
      1
    ],
    [
      6,
      6,
      1
    ]
  ],
  "move_limit": 22,
  "num_colors": 5,
  "preplaced": [
    [
      0,
      3,
      "rocket_h",
      1
    ],
    [
      7,
      3,
      "rocket_h",
      3
    ]
  ],
  "score_stars": [
    900,
    2200,
    3500
  ],
  "size": [
    8,
    8
  ]
}